dataprocessing/__init__.py
dataprocessing/core.py
dataprocessing/exceptions.py
dataprocessing/live_data.py
dataprocessing/readers.py
dataprocessing/simple_import.py
dataprocessing/simple_live.py
dataprocessing/sql.py
dataprocessing/utils.py
dataprocessing/validators.py
dataprocessing/writers.py
dataprocesslite-0.1.0.dist-info/licenses/LICENSE
dataprocesslite-0.1.0.dist-info/METADATA
dataprocesslite-0.1.0.dist-info/WHEEL
dataprocesslite-0.1.0.dist-info/top_level.txt
dataprocesslite-0.1.0.dist-info/RECORD
