Metadata-Version: 2.4
Name: dataprocesslite
Version: 0.1.0
Summary: A user-friendly Python package for working with CSV data
Home-page: https://github.com/conorzen/dataprocess
Author: Conor Reidy
Author-email: conor@example.com
Project-URL: Bug Reports, https://github.com/conorzen/dataprocess/issues
Project-URL: Source, https://github.com/conorzen/dataprocess
Project-URL: Documentation, https://github.com/conorzen/dataprocess#readme
Keywords: csv,data,processing,pandas,sql,live-data
Classifier: Development Status :: 4 - Beta
Classifier: Intended Audience :: Developers
Classifier: Intended Audience :: Science/Research
Classifier: License :: OSI Approved :: MIT License
Classifier: Operating System :: OS Independent
Classifier: Programming Language :: Python :: 3
Classifier: Programming Language :: Python :: 3.8
Classifier: Programming Language :: Python :: 3.9
Classifier: Programming Language :: Python :: 3.10
Classifier: Programming Language :: Python :: 3.11
Classifier: Topic :: Scientific/Engineering :: Information Analysis
Classifier: Topic :: Software Development :: Libraries :: Python Modules
Requires-Python: >=3.8
License-File: LICENSE
Requires-Dist: pandas>=1.5.0
Requires-Dist: chardet>=4.0.0
Requires-Dist: python-dateutil>=2.8.0
Requires-Dist: numpy>=1.21.0
Requires-Dist: openpyxl>=3.0.0
Requires-Dist: pyarrow>=7.0.0
Requires-Dist: requests>=2.25.0
Requires-Dist: psycopg2-binary>=2.9.0
Requires-Dist: mysql-connector-python>=8.0.0
Provides-Extra: fast
Requires-Dist: polars>=0.19.0; extra == "fast"
Dynamic: author
Dynamic: author-email
Dynamic: classifier
Dynamic: description
Dynamic: description-content-type
Dynamic: home-page
Dynamic: keywords
Dynamic: license-file
Dynamic: project-url
Dynamic: provides-extra
Dynamic: requires-dist
Dynamic: requires-python
Dynamic: summary
